diaad/__init__.py
diaad/cli.py
diaad/deprecated.py
diaad/main.py
diaad/run_wrappers.py
diaad/POWERS/__init__.py
diaad/POWERS/automation_validation.py
diaad/POWERS/powers_coding_analysis.py
diaad/POWERS/powers_coding_files.py
diaad/convo_turns/__init__.py
diaad/convo_turns/digital_convo_turns_analysis.py
diaad/utils/__init__.py
diaad/utils/auxiliary.py
diaad-0.2.2.dist-info/licenses/LICENSE.txt
diaad-0.2.2.dist-info/METADATA
diaad-0.2.2.dist-info/WHEEL
diaad-0.2.2.dist-info/entry_points.txt
diaad-0.2.2.dist-info/top_level.txt
diaad-0.2.2.dist-info/RECORD
