Metadata-Version: 2.4
Name: diaad
Version: 0.2.2
Summary: DEPRECATED: Former name of the TAALCR project. Please see the TAALCR repository.
Author: Nick McCloskey
License: MIT
Project-URL: Homepage, https://github.com/<nmccloskey>/TAALCR
Project-URL: Repository, https://github.com/nmccloskey/TAALCR
Project-URL: Issues, https://github.com/nmccloskey/TAALCR/issues
Project-URL: Documentation, https://github.com/nmccloskey/TAALCR
Classifier: Development Status :: 7 - Inactive
Classifier: Programming Language :: Python :: 3
Classifier: License :: OSI Approved :: MIT License
Classifier: Operating System :: OS Independent
Requires-Python: >=3.12
License-File: LICENSE.txt
Dynamic: license-file
